ftp2bq_zfullio/__init__.py
ftp2bq_zfullio/ftp.py
ftp2bq_zfullio/general.py
ftp2bq_zfullio/sftp.py
ftp2bq_zfullio-1.1.0.dist-info/LICENSE
ftp2bq_zfullio-1.1.0.dist-info/METADATA
ftp2bq_zfullio-1.1.0.dist-info/WHEEL
ftp2bq_zfullio-1.1.0.dist-info/RECORD
