Metadata-Version: 2.1
Name: ftp2bq-zfullio
Version: 1.1.0
Summary: 
Author: viktor
Author-email: vi.dave@yandex.ru
Requires-Python: >=3.10,<3.11
Classifier: Programming Language :: Python :: 3
Classifier: Programming Language :: Python :: 3.10
Requires-Dist: bq-easy-zfullio (>=1,<2)
Requires-Dist: loguru (>=0,<1)
Requires-Dist: openpyxl (>=3,<4)
Requires-Dist: pandas (>=2,<3)
Requires-Dist: paramiko (>=3,<4)
Requires-Dist: xmltodict (>=0.13.0,<0.14.0)
